jinja_gcs_loader/__init__.py
jinja_gcs_loader/jinja_gcs_loader.py
jinja_gcs_loader-0.0.17.dist-info/LICENSE
jinja_gcs_loader-0.0.17.dist-info/METADATA
jinja_gcs_loader-0.0.17.dist-info/WHEEL
jinja_gcs_loader-0.0.17.dist-info/top_level.txt
jinja_gcs_loader-0.0.17.dist-info/RECORD
