Metadata-Version: 2.1
Name: jinja-gcs-loader
Version: 0.0.17
Summary: Simple Jinja2 GCS Template Loader
Home-page: https://github.com/ptfpinho23/jinja2-gcs-loader
Author: Pedro Pinho
Author-email: ptfpinho@hotmail.com
License: UNKNOWN
Platform: UNKNOWN
Classifier: Programming Language :: Python :: 3
Classifier: License :: OSI Approved :: MIT License
Classifier: Operating System :: OS Independent
License-File: LICENSE
Requires-Dist: google-cloud
Requires-Dist: Jinja2
Requires-Dist: google
